[
  {
    "serviceId": 1,
    "serviceName": "Winter Coat Fitting for Dogs",
    "providerName": "PawCare Studio",
    "providerEmail": "info@pawcare.com",
    "price": 25,
    "rating": 4.9,
    "slotsAvailable": 4,
    "description": "Custom coat fitting and warm outfit options to keep your dog comfortable in the cold.",
    "image": "https://i.postimg.cc/3x3x3/example1.png",
    "category": "Clothing"
  },
  {
    "serviceId": 2,
    "serviceName": "Winter Grooming & Paw Treatment",
    "providerName": "CozyPets Grooming",
    "providerEmail": "hello@cozypets.com",
    "price": 30,
    "rating": 4.8,
    "slotsAvailable": 3,
    "description": "Professional grooming with moisturizing paw balm and winter-safe shampoo.",
    "image": "https://i.postimg.cc/3x3x3/example2.png",
    "category": "Grooming"
  },
  {
    "serviceId": 3,
    "serviceName": "Hypoallergenic Winter Shampoo",
    "providerName": "GentlePaws",
    "providerEmail": "contact@gentlepaws.com",
    "price": 18,
    "rating": 4.7,
    "slotsAvailable": 6,
    "description": "Warm-water bath with a gentle, moisturizing shampoo designed for winter skin.",
    "image": "https://i.postimg.cc/3x3x3/example3.png",
    "category": "Grooming"
  },
  {
    "serviceId": 4,
    "serviceName": "Heated Pet Bed Rental",
    "providerName": "WarmNook",
    "providerEmail": "rentals@warmnook.com",
    "price": 8,
    "rating": 4.6,
    "slotsAvailable": 10,
    "description": "Short-term rental of safe, low-voltage heated pet beds for small/medium pets.",
    "image": "https://i.postimg.cc/3x3x3/example4.png",
    "category": "Supplies"
  },
  {
    "serviceId": 5,
    "serviceName": "Paw Wax & Protection",
    "providerName": "PawArmor",
    "providerEmail": "care@pawarmor.com",
    "price": 12,
    "rating": 4.85,
    "slotsAvailable": 5,
    "description": "Protective paw wax to shield paws from salt and cold cracking.",
    "image": "https://i.postimg.cc/3x3x3/example5.png",
    "category": "Health"
  },
  {
    "serviceId": 6,
    "serviceName": "Cold-Weather Nutrition Consult",
    "providerName": "NutriPets",
    "providerEmail": "diet@nutripets.com",
    "price": 20,
    "rating": 4.9,
    "slotsAvailable": 2,
    "description": "Vet-backed nutrition advice to adjust caloric intake during cold months.",
    "image": "https://i.postimg.cc/3x3x3/example6.png",
    "category": "Health"
  },
  {
    "serviceId": 7,
    "serviceName": "Short-Walk Dog Service (Safe Winter Routes)",
    "providerName": "SnowTrail Walkers",
    "providerEmail": "walks@snowtrail.com",
    "price": 15,
    "rating": 4.75,
    "slotsAvailable": 7,
    "description": "Short neighborhood walks using cleared/treated routes to avoid ice hazards.",
    "image": "https://i.postimg.cc/3x3x3/example7.png",
    "category": "Services"
  },
  {
    "serviceId": 8,
    "serviceName": "Indoor Play Sessions",
    "providerName": "PlayPaws Center",
    "providerEmail": "book@playpaws.com",
    "price": 10,
    "rating": 4.65,
    "slotsAvailable": 8,
    "description": "Supervised indoor play to keep pets active when it's too cold outside.",
    "image": "https://i.postimg.cc/3x3x3/example8.png",
    "category": "Services"
  },
  {
    "serviceId": 9,
    "serviceName": "Emergency Cold-Exposure Check-up",
    "providerName": "QuickVet Clinic",
    "providerEmail": "urgent@quickvet.com",
    "price": 35,
    "rating": 4.9,
    "slotsAvailable": 1,
    "description": "Quick checks for hypothermia signs and immediate supportive care.",
    "image": "https://i.postimg.cc/3x3x3/example9.png",
    "category": "Health"
  },
  {
    "serviceId": 10,
    "serviceName": "Reflective Winter Leash & Collar Set",
    "providerName": "NightWalk Gear",
    "providerEmail": "sales@nightwalk.com",
    "price": 22,
    "rating": 4.5,
    "slotsAvailable": 12,
    "description": "Reflective gear for safe evening walks in shorter daylight.",
    "image": "https://i.postimg.cc/3x3x3/example10.png",
    "category": "Supplies"
  },
  {
    "serviceId": 11,
    "serviceName": "Senior Pet Warm-Home Visits",
    "providerName": "KindCare Visits",
    "providerEmail": "visits@kindcare.com",
    "price": 28,
    "rating": 4.95,
    "slotsAvailable": 2,
    "description": "In-home temperature checks and cuddle time for senior pets.",
    "image": "https://i.postimg.cc/3x3x3/example11.png",
    "category": "Services"
  },
  {
    "serviceId": 12,
    "serviceName": "Cozy Cat Sweater Custom",
    "providerName": "KittyKnit",
    "providerEmail": "orders@kittyknit.com",
    "price": 20,
    "rating": 4.6,
    "slotsAvailable": 4,
    "description": "Handmade, soft sweaters sized specially for indoor cats.",
    "image": "https://i.postimg.cc/3x3x3/example12.png",
    "category": "Clothing"
  },
  {
    "serviceId": 13,
    "serviceName": "Winter Hydration Pack (Supplements)",
    "providerName": "HydraPets",
    "providerEmail": "support@hydrapets.com",
    "price": 14,
    "rating": 4.4,
    "slotsAvailable": 20,
    "description": "Electrolyte supplements and tips for keeping pets hydrated in winter.",
    "image": "https://i.postimg.cc/3x3x3/example13.png",
    "category": "Health"
  },
  {
    "serviceId": 14,
    "serviceName": "Short-Claw Trim & Paw Check",
    "providerName": "SafeClip Groomers",
    "providerEmail": "info@safeclip.com",
    "price": 12,
    "rating": 4.7,
    "slotsAvailable": 6,
    "description": "Trimming claws and checking paw pads for salt or iceballing.",
    "image": "https://i.postimg.cc/3x3x3/example14.png",
    "category": "Grooming"
  },
  {
    "serviceId": 15,
    "serviceName": "Cold-Weather Daycare (Half Day)",
    "providerName": "WarmDays Daycare",
    "providerEmail": "hello@warmdays.com",
    "price": 18,
    "rating": 4.6,
    "slotsAvailable": 9,
    "description": "Indoor daycare with temperature control and winter-safe play areas.",
    "image": "https://i.postimg.cc/3x3x3/example15.png",
    "category": "Services"
  }
]
